__init__.py
arr_fun.py
atr_mgr.py
binning.py
cf_checker.py
collector.py
compare_files.py
data_splitter.py
dump_output.py
find_ganga_job.py
fit_manager.py
fitter.py
ganga_stats.py
hep_cl.py
hep_gb.py
log_store.py
mcpull.py
misid_check.py
model_analyzer.py
ndict.py
pathfinder.py
pdg_utils.py
plot_fit.py
plotter.py
progress.py
rdf_loader.py
stat_indep.py
stream_dump.py
style.py
sweight_serialize.py
tmva_log_reader.py
trgwgt.py
utils.py
utils_noroot.py
utils_py2.py
var_plotter.py
version_management.py
plotting/utilities.py
rx_scripts-0.3.8.data/scripts/cdr_copy
rx_scripts-0.3.8.data/scripts/check_size
rx_scripts-0.3.8.data/scripts/check_tuples
rx_scripts-0.3.8.data/scripts/compare_files
rx_scripts-0.3.8.data/scripts/copy_tstruc
rx_scripts-0.3.8.data/scripts/copy_tuples
rx_scripts-0.3.8.data/scripts/download_from_jobid
rx_scripts-0.3.8.data/scripts/dv_stats
rx_scripts-0.3.8.data/scripts/jmanager
rx_scripts-0.3.8.data/scripts/job_copy
rx_scripts-0.3.8.data/scripts/job_run_commands
rx_scripts-0.3.8.data/scripts/kerberos
rx_scripts-0.3.8.data/scripts/link_files
rx_scripts-0.3.8.data/scripts/link_to_file
rx_scripts-0.3.8.data/scripts/list_branches
rx_scripts-0.3.8.data/scripts/print_trees
rx_scripts-0.3.8.data/scripts/run_copy
rx_scripts-0.3.8.data/scripts/submit_run_commands
rx_scripts-0.3.8.data/scripts/tar_plots
scripts_data/__init__.py
scripts_data/misid_data/__init__.py
scripts_data/misid_data/bpd0kpienu.json
scripts_data/tests_data/find_ganga_job.json
stats/average.py
stats/correlations.py
stats/covariance.py
stats/nll_plot.py
stats/pdf.py
stats/utils.py
zutils/pdf.py
zutils/plot.py
zutils/utils.py
rx_scripts-0.3.8.dist-info/METADATA
rx_scripts-0.3.8.dist-info/WHEEL
rx_scripts-0.3.8.dist-info/top_level.txt
rx_scripts-0.3.8.dist-info/RECORD
