Metadata-Version: 2.1
Name: rx_scripts
Version: 0.3.8
Summary: Generic utilities for data analysis
Requires-Dist: scipy
Requires-Dist: sympy
Requires-Dist: mplhep
Requires-Dist: hist
Requires-Dist: pandas
Requires-Dist: zfit >=0.14.0
Requires-Dist: dill
Requires-Dist: iminuit >=2.20.0
Requires-Dist: awkward ==2.4.6
Requires-Dist: particle
Requires-Dist: vector
Requires-Dist: pdg
